COPYING
MANIFEST.in
README
setup.py
src/cmsplugin_blurp/__init__.py
src/cmsplugin_blurp/app_settings.py
src/cmsplugin_blurp/tests.py
src/cmsplugin_blurp/utils.py
src/cmsplugin_blurp/locale/fr/LC_MESSAGES/django.mo
src/cmsplugin_blurp/locale/fr/LC_MESSAGES/django.po
src/cmsplugin_blurp/renderers/__init__.py
src/cmsplugin_blurp/renderers/base.py
src/cmsplugin_blurp/renderers/data_source.py
src/cmsplugin_blurp/renderers/data_source_list.py
src/cmsplugin_blurp/renderers/signature.py
src/cmsplugin_blurp/renderers/sql.py
src/cmsplugin_blurp/renderers/static.py
src/cmsplugin_blurp/renderers/template.py
src/cmsplugin_blurp/templates/cmsplugin_blurp/template_not_found.html
src/cmsplugin_blurp/templatetags/__init__.py
src/cmsplugin_blurp/templatetags/blurp_tags.py
src/cmsplugin_blurp/tests_data/json
src/cmsplugin_blurp/tests_data/raw
src/cmsplugin_blurp/tests_data/rss
src/cmsplugin_blurp/tests_data/xml
src/django_cmsplugin_blurp.egg-info/PKG-INFO
src/django_cmsplugin_blurp.egg-info/SOURCES.txt
src/django_cmsplugin_blurp.egg-info/dependency_links.txt
src/django_cmsplugin_blurp.egg-info/requires.txt
src/django_cmsplugin_blurp.egg-info/top_level.txt