Metadata-Version: 1.0
Name: django-cmsplugin-blurp
Version: 1.18
Summary: UNKNOWN
Home-page: http://dev.entrouvert.org/projects/django-cmsplugin-blurp/
Author: Benjamin Dauvergne
Author-email: bdauvergne@entrouvert.com
License: AGPLv3 or later
Platform: UNKNOWN
